{
	"configurations" : 
	[
		{
			"directories" : 
			[
				{
					"build" : ".",
					"jsonFile" : "directory-.-Debug-d0094a50bb2071803777.json",
					"minimumCMakeVersion" : 
					{
						"string" : "3.21"
					},
					"projectIndex" : 0,
					"source" : ".",
					"targetIndexes" : 
					[
						0
					]
				}
			],
			"name" : "Debug",
			"projects" : 
			[
				{
					"directoryIndexes" : 
					[
						0
					],
					"name" : "Assignment1",
					"targetIndexes" : 
					[
						0
					]
				}
			],
			"targets" : 
			[
				{
					"directoryIndex" : 0,
					"id" : "Assignment1::@6890427a1f51a3e7e1df",
					"jsonFile" : "target-Assignment1-Debug-5ef5f0633c06f039a386.json",
					"name" : "Assignment1",
					"projectIndex" : 0
				}
			]
		}
	],
	"kind" : "codemodel",
	"paths" : 
	{
		"build" : "E:/ITProgrammingFall2022/PROG/Assignment1/cmake-build-debug",
		"source" : "E:/ITProgrammingFall2022/PROG/Assignment1"
	},
	"version" : 
	{
		"major" : 2,
		"minor" : 3
	}
}
